rtl/ALU.v
module ALU(
    input [3:0] ALU_Sel,
    input [31:0] operand_0,
    input [31:0] operand_1,
    output reg [31:0] result
);

localparam ADD              = 4'b0000; 
localparam SUB              = 4'b0001; 

localparam AND              = 4'b0010;
localparam OR               = 4'b0011;
localparam XOR              = 4'b0100;

localparam SHL_LOGICAL      = 4'b0110;
localparam SHR_LOGICAL      = 4'b0111;
localparam SHR_ARITHMETIC   = 4'b1000;

localparam LESS_THAN    = 4'b1001;

always @(*) begin
    case (ALU_Sel)
        ADD: result = operand_0 + operand_1;
        SUB: result = operand_0 - operand_1;
        
        AND: result = operand_0 & operand_1;
        OR:  result = operand_0 | operand_1;
        XOR: result = operand_0 ^ operand_1;

        SHL_LOGICAL: result = operand_0 << operand_1[4:0];
        SHR_LOGICAL: result = operand_0 >> operand_1[4:0];
        SHR_ARITHMETIC: result = operand_0 >>> operand_1[4:0];

        LESS_THAN: result = ($signed(operand_0) < $signed(operand_1)) ? 32'b1 : 32'b0;
        
        default: result = 32'b0;
    endcase
end


endmodule

test/test_ALU.v
module test_ALU();
    reg [3:0] ALU_Sel;
    reg [31:0] operand_0;
    reg [31:0] operand_1;
    wire [31:0] result;

    ALU DUT(
        .ALU_Sel(ALU_Sel),
        .operand_0(operand_0),
        .operand_1(operand_1),
        .result(result)
    );

//__________________________ALU ALU_Sels_____________________________//
    localparam ADD              = 4'b0000; 
    localparam SUB              = 4'b0001; 
    localparam AND              = 4'b0010;
    localparam OR               = 4'b0011;
    localparam XOR              = 4'b0100;
    localparam SHL_LOGICAL      = 4'b0101;
    localparam SHR_LOGICAL      = 4'b0110;
    localparam SHR_ARITHMETIC   = 4'b0111;
    localparam LESS_THAN        = 4'b1000;

//______________________Testcase location___________________________//
    localparam ADD_OPERAND_0            = "../test/input_data/ADD_OPERAND_0.txt";
    localparam ADD_OPERAND_1            = "../test/input_data/ADD_OPERAND_1.txt";
    localparam ADD_RESULT               = "../test/input_data/ADD_RESULT.txt";

    localparam SUB_OPERAND_0            = "../test/input_data/SUB_OPERAND_0.txt";
    localparam SUB_OPERAND_1            = "../test/input_data/SUB_OPERAND_1.txt";
    localparam SUB_RESULT               = "../test/input_data/SUB_RESULT.txt";

    localparam BITWISE_OPERAND_0        = "../test/input_data/BITWISE_OPERAND_0.txt";
    localparam BITWISE_OPERAND_1        = "../test/input_data/BITWISE_OPERAND_1.txt";
    localparam AND_RESULT               = "../test/input_data/AND_RESULT.txt";
    localparam OR_RESULT                = "../test/input_data/OR_RESULT.txt";
    localparam XOR_RESULT               = "../test/input_data/XOR_RESULT.txt";

    localparam SHL_LOGICAL_OPERAND_0    = "../test/input_data/SHL_LOGICAL_OPERAND_0.txt";
    localparam SHL_LOGICAL_OPERAND_1    = "../test/input_data/SHL_LOGICAL_OPERAND_1.txt";
    localparam SHL_LOGICAL_RESULT       = "../test/input_data/SHL_LOGICAL_RESULT.txt";

    localparam SHR_LOGICAL_OPERAND_0    = "../test/input_data/SHR_LOGICAL_OPERAND_0.txt";
    localparam SHR_LOGICAL_OPERAND_1    = "../test/input_data/SHR_LOGICAL_OPERAND_1.txt";
    localparam SHR_LOGICAL_RESULT       = "../test/input_data/SHR_LOGICAL_RESULT.txt";

    localparam SHR_ARITHMETIC_OPERAND_0 = "../test/input_data/SHR_ARITHMETIC_OPERAND_0.txt";
    localparam SHR_ARITHMETIC_OPERAND_1 = "../test/input_data/SHR_ARITHMETIC_OPERAND_1.txt";
    localparam SHR_ARITHMETIC_RESULT    = "../test/input_data/SHR_ARITHMETIC_RESULT.txt";

    localparam LESS_THAN_OPERAND_0      = "../test/input_data/LESS_THAN_OPERAND_0.txt";
    localparam LESS_THAN_OPERAND_1      = "../test/input_data/LESS_THAN_OPERAND_1.txt";
    localparam LESS_THAN_RESULT         = "../test/input_data/LESS_THAN_RESULT.txt";

//________________Testcase input & Golden output____________________//
    reg [31:0] ADD_operand_0 [0:1000];
    reg [31:0] ADD_operand_1 [0:1000];
    reg [31:0] ADD_result [0:1000];

    reg [31:0] SUB_operand_0 [0:1000];
    reg [31:0] SUB_operand_1 [0:1000];
    reg [31:0] SUB_result [0:1000];

    reg [31:0] BITWISE_operand_0 [0:1000];
    reg [31:0] BITWISE_operand_1 [0:1000];
    reg [31:0] AND_result [0:1000];
    reg [31:0] OR_result [0:1000];
    reg [31:0] XOR_result [0:1000];

    reg [31:0] SHL_LOGICAL_operand_0 [0:1000];
    reg [31:0] SHL_LOGICAL_operand_1 [0:1000];
    reg [31:0] SHL_LOGICAL_result [0:1000];

    reg [31:0] SHR_LOGICAL_operand_0 [0:1000];
    reg [31:0] SHR_LOGICAL_operand_1 [0:1000];
    reg [31:0] SHR_LOGICAL_result [0:1000];

    reg [31:0] SHR_ARITHMETIC_operand_0 [0:1000];
    reg [31:0] SHR_ARITHMETIC_operand_1 [0:1000];
    reg [31:0] SHR_ARITHMETIC_result [0:1000];

    reg [31:0] LESS_THAN_operand_0 [0:1000];
    reg [31:0] LESS_THAN_operand_1 [0:1000];
    reg [31:0] LESS_THAN_result [0:1000];

integer result_ADD, result_SUB, result_AND, result_OR, result_XOR;
integer result_SHL_LOGICAL, result_SHR_LOGICAL, result_SHR_ARITHMETIC, result_LESS_THAN;

integer j;
//_____________________Read testcase input__________________________//
    initial begin
        $readmemh(ADD_OPERAND_0, ADD_operand_0);
        $readmemh(ADD_OPERAND_1, ADD_operand_1);
        $readmemh(ADD_RESULT, ADD_result);

        $readmemh(SUB_OPERAND_0, SUB_operand_0);
        $readmemh(SUB_OPERAND_1, SUB_operand_1);
        $readmemh(SUB_RESULT, SUB_result);

        $readmemh(BITWISE_OPERAND_0, BITWISE_operand_0);
        $readmemh(BITWISE_OPERAND_1, BITWISE_operand_1);
        // for(j = 0; j < 1000; j = j+1) begin
        //     $display("%d", BITWISE_operand_0[j]);
        //     // $display("%d", BITWISE_operand_1[j]);
        // end

        $readmemh(AND_RESULT, AND_result);
        $readmemh(OR_RESULT, OR_result);
        $readmemh(XOR_RESULT, XOR_result);

        $readmemh(SHL_LOGICAL_OPERAND_0, SHL_LOGICAL_operand_0);
        $readmemh(SHL_LOGICAL_OPERAND_1, SHL_LOGICAL_operand_1);
        $readmemh(SHL_LOGICAL_RESULT, SHL_LOGICAL_result);

        $readmemh(SHR_LOGICAL_OPERAND_0, SHR_LOGICAL_operand_0);
        $readmemh(SHR_LOGICAL_OPERAND_1, SHR_LOGICAL_operand_1);
        $readmemh(SHR_LOGICAL_RESULT, SHR_LOGICAL_result);

        $readmemh(SHR_ARITHMETIC_OPERAND_0, SHR_ARITHMETIC_operand_0);
        $readmemh(SHR_ARITHMETIC_OPERAND_1, SHR_ARITHMETIC_operand_1);
        $readmemh(SHR_ARITHMETIC_RESULT, SHR_ARITHMETIC_result);

        $readmemh(LESS_THAN_OPERAND_0, LESS_THAN_operand_0);
        $readmemh(LESS_THAN_OPERAND_1, LESS_THAN_operand_1);
        $readmemh(LESS_THAN_RESULT, LESS_THAN_result);
        
        $dumpfile("../sim/dumpfile/ALU_wave.vcd");
        $dumpvars(0, test_ALU);

        result_ADD = 0;
        result_SUB = 0;
        result_AND = 0;
        result_OR = 0;
        result_XOR = 0;
        result_SHL_LOGICAL = 0;
        result_SHR_LOGICAL = 0;
        result_SHR_ARITHMETIC = 0;
        result_LESS_THAN = 0;
    end

//_______________________Drive input task___________________________//
    task drive_input;
        input [3:0] ALU_Sel_t;
        input [31:0] operand_0_t;
        input [31:0] operand_1_t;
        begin
            operand_0 = operand_0_t;
            operand_1 = operand_1_t;
            ALU_Sel = ALU_Sel_t;
            #1;
        end
    endtask

    task check_output;
        input [31:0] expected_result;
        input [31:0] result;
        inout integer check_result;
        begin
            if (result !== expected_result) begin
                $display("Test failed: %d != %d", result, expected_result);
            end else begin
                check_result = check_result + 1;
            end
        end
    endtask

//__________________________Run testcase____________________________//

    integer i;
    initial begin
        for(i = 0; i < 1000; i = i+1) begin
            drive_input(ADD, ADD_operand_0[i], ADD_operand_1[i]);
            if(result!= ADD_result[i])$display("ADD %d: %d + %d = %d, expected: %d ", i, ADD_operand_0[i], ADD_operand_1[i], result, ADD_result[i]);
            check_output(ADD_result[i], result, result_ADD);
        end
        
        for(i = 0; i < 1000; i = i+1) begin
            drive_input(SUB, SUB_operand_0[i], SUB_operand_1[i]);
            if(result!= SUB_result[i])$display("SUB %d: %d - %d = %d, expected: %d ", i, SUB_operand_0[i], SUB_operand_1[i], result, SUB_result[i]);
            check_output(SUB_result[i], result, result_SUB);
        end

        for(i = 0; i < 1000; i = i+1) begin
            drive_input(AND, BITWISE_operand_0[i], BITWISE_operand_1[i]);
            if(result!= AND_result[i])$display("AND %d: %d & %d = %d, expected: %d ", i, BITWISE_operand_0[i], BITWISE_operand_1[i], result, AND_result[i]);
            check_output(AND_result[i], result, result_AND);
        end

        for(i = 0; i < 1000; i = i+1) begin
            drive_input(OR, BITWISE_operand_0[i], BITWISE_operand_1[i]);
            if(result!= OR_result[i])$display("OR %d: %d | %d = %d, expected: %d ", i, BITWISE_operand_0[i], BITWISE_operand_1[i], result, OR_result[i]);
            check_output(OR_result[i], result, result_OR);
        end

        for(i = 0; i < 1000; i = i+1) begin
            drive_input(XOR, BITWISE_operand_0[i], BITWISE_operand_1[i]);
            if(result!= XOR_result[i])$display("XOR %d: %d ^ %d = %d, expected: %d ", i, BITWISE_operand_0[i], BITWISE_operand_1[i], result, XOR_result[i]);
            check_output(XOR_result[i], result, result_XOR);
        end

        for(i = 0; i < 1000; i = i+1) begin
            drive_input(SHL_LOGICAL, SHL_LOGICAL_operand_0[i], SHL_LOGICAL_operand_1[i]);
            if(result!= SHL_LOGICAL_result[i])$display("SHL_LOGICAL %d: %b << %d = %b, expected: %b ", i, SHL_LOGICAL_operand_0[i], SHL_LOGICAL_operand_1[i][4:0], result, SHL_LOGICAL_result[i]);
            check_output(SHL_LOGICAL_result[i], result, result_SHL_LOGICAL);
        end

        for(i = 0; i < 1000; i = i+1) begin
            drive_input(SHR_LOGICAL, SHR_LOGICAL_operand_0[i], SHR_LOGICAL_operand_1[i]);
            if(result!= SHR_LOGICAL_result[i])$display("SHR_LOGICAL %d: %b >> %d = %b, expected: %b ", i, SHR_LOGICAL_operand_0[i], SHR_LOGICAL_operand_1[i][4:0], result, SHR_LOGICAL_result[i]);
            check_output(SHR_LOGICAL_result[i], result, result_SHR_LOGICAL);
        end

        for(i = 0; i < 1000; i = i+1) begin
            drive_input(SHR_ARITHMETIC, SHR_ARITHMETIC_operand_0[i], SHR_ARITHMETIC_operand_1[i]);
            if(result!= SHR_ARITHMETIC_result[i])$display("Failed SHR_ARITHMETIC %d: %b >>> %d = %b, expected: %b ", i, SHR_ARITHMETIC_operand_0[i], SHR_ARITHMETIC_operand_1[i][4:0], result, SHR_ARITHMETIC_result[i]);
            check_output(SHR_ARITHMETIC_result[i], result, result_SHR_ARITHMETIC);
        end

        for(i = 0; i < 1000; i = i+1) begin
            drive_input(LESS_THAN, LESS_THAN_operand_0[i], LESS_THAN_operand_1[i]);
            if(result!= LESS_THAN_result[i])$display("LESS_THAN %d: %d < %d = %b, expected: %b ", i, $signed(LESS_THAN_operand_0[i]), $signed(LESS_THAN_operand_1[i]), result, LESS_THAN_result[i]);
            check_output(LESS_THAN_result[i], result, result_LESS_THAN);
        end

        #1;
        $display("Test completed.");
        $display("ADD: %d tests passed", result_ADD);
        $display("SUB: %d tests passed", result_SUB);
        $display("AND: %d tests passed", result_AND);
        $display("OR: %d tests passed", result_OR);
        $display("XOR: %d tests passed", result_XOR);
        $display("SHL_LOGICAL: %d tests passed", result_SHL_LOGICAL);
        $display("SHR_LOGICAL: %d tests passed", result_SHR_LOGICAL);
        $display("SHR_ARITHMETIC: %d tests passed", result_SHR_ARITHMETIC);
        $display("LESS_THAN: %d tests passed", result_LESS_THAN);
        $finish;
    end


endmodule

sim/dumpfile/ALU_wave.vcd
$date
	Wed Apr 16 17:26:45 2025
$end
$version
	QuestaSim Version 2021.1
$end
$timescale
	1ns
$end

$scope module test_ALU $end
$var parameter 4 ! ADD $end
$var parameter 4 " SUB $end
$var parameter 4 # AND $end
$var parameter 4 $ OR $end
$var parameter 4 % XOR $end
$var parameter 4 & SHL_LOGICAL $end
$var parameter 4 ' SHR_LOGICAL $end
$var parameter 4 ( SHR_ARITHMETIC $end
$var parameter 4 ) LESS_THAN $end
$var parameter 288 * ADD_OPERAND_0 $end
$var parameter 288 + ADD_OPERAND_1 $end
$var parameter 264 , ADD_RESULT $end
$var parameter 288 - SUB_OPERAND_0 $end
$var parameter 288 . SUB_OPERAND_1 $end
$var parameter 264 / SUB_RESULT $end
$var parameter 320 0 BITWISE_OPERAND_0 $end
$var parameter 320 1 BITWISE_OPERAND_1 $end
$var parameter 264 2 AND_RESULT $end
$var parameter 256 3 OR_RESULT $end
$var parameter 264 4 XOR_RESULT $end
$var parameter 352 5 SHL_LOGICAL_OPERAND_0 $end
$var parameter 352 6 SHL_LOGICAL_OPERAND_1 $end
$var parameter 328 7 SHL_LOGICAL_RESULT $end
$var parameter 352 8 SHR_LOGICAL_OPERAND_0 $end
$var parameter 352 9 SHR_LOGICAL_OPERAND_1 $end
$var parameter 328 : SHR_LOGICAL_RESULT $end
$var parameter 376 ; SHR_ARITHMETIC_OPERAND_0 $end
$var parameter 376 < SHR_ARITHMETIC_OPERAND_1 $end
$var parameter 352 = SHR_ARITHMETIC_RESULT $end
$var parameter 336 > LESS_THAN_OPERAND_0 $end
$var parameter 336 ? LESS_THAN_OPERAND_1 $end
$var parameter 312 @ LESS_THAN_RESULT $end
$var reg 4 A ALU_Sel [3:0] $end
$var reg 32 B operand_0 [31:0] $end
$var reg 32 C operand_1 [31:0] $end
$var wire 1 D result [31] $end
$var wire 1 E result [30] $end
$var wire 1 F result [29] $end
$var wire 1 G result [28] $end
$var wire 1 H result [27] $end
$var wire 1 I result [26] $end
$var wire 1 J result [25] $end
$var wire 1 K result [24] $end
$var wire 1 L result [23] $end
$var wire 1 M result [22] $end
$var wire 1 N result [21] $end
$var wire 1 O result [20] $end
$var wire 1 P result [19] $end
$var wire 1 Q result [18] $end
$var wire 1 R result [17] $end
$var wire 1 S result [16] $end
$var wire 1 T result [15] $end
$var wire 1 U result [14] $end
$var wire 1 V result [13] $end
$var wire 1 W result [12] $end
$var wire 1 X result [11] $end
$var wire 1 Y result [10] $end
$var wire 1 Z result [9] $end
$var wire 1 [ result [8] $end
$var wire 1 \ result [7] $end
$var wire 1 ] result [6] $end
$var wire 1 ^ result [5] $end
$var wire 1 _ result [4] $end
$var wire 1 ` result [3] $end
$var wire 1 a result [2] $end
$var wire 1 b result [1] $end
$var wire 1 c result [0] $end
$var integer 32 d result_ADD $end
$var integer 32 e result_SUB $end
$var integer 32 f result_AND $end
$var integer 32 g result_OR $end
$var integer 32 h result_XOR $end
$var integer 32 i result_SHL_LOGICAL $end
$var integer 32 j result_SHR_LOGICAL $end
$var integer 32 k result_SHR_ARITHMETIC $end
$var integer 32 l result_LESS_THAN $end
$var integer 32 m j $end
$var integer 32 n i $end

$scope task drive_input $end
$var reg 4 o ALU_Sel_t [3:0] $end
$var reg 32 p operand_0_t [31:0] $end
$var reg 32 q operand_1_t [31:0] $end
$upscope $end

$scope task check_output $end
$var reg 32 r expected_result [31:0] $end
$var reg 32 s result [31:0] $end
$var integer 32 t check_result $end
$upscope $end

$scope module DUT $end
$var parameter 4 u ADD $end
$var parameter 4 v SUB $end
$var parameter 4 w AND $end
$var parameter 4 x OR $end
$var parameter 4 y XOR $end
$var parameter 4 z SHL_LOGICAL $end
$var parameter 4 { SHR_LOGICAL $end
$var parameter 4 | SHR_ARITHMETIC $end
$var parameter 4 } LESS_THAN $end
$var wire 1 ~ ALU_Sel [3] $end
$var wire 1 !! ALU_Sel [2] $end
$var wire 1 "! ALU_Sel [1] $end
$var wire 1 #! ALU_Sel [0] $end
$var wire 1 $! operand_0 [31] $end
$var wire 1 %! operand_0 [30] $end
$var wire 1 &! operand_0 [29] $end
$var wire 1 '! operand_0 [28] $end
$var wire 1 (! operand_0 [27] $end
$var wire 1 )! operand_0 [26] $end
$var wire 1 *! operand_0 [25] $end
$var wire 1 +! operand_0 [24] $end
$var wire 1 ,! operand_0 [23] $end
$var wire 1 -! operand_0 [22] $end
$var wire 1 .! operand_0 [21] $end
$var wire 1 /! operand_0 [20] $end
$var wire 1 0! operand_0 [19] $end
$var wire 1 1! operand_0 [18] $end
$var wire 1 2! operand_0 [17] $end
$var wire 1 3! operand_0 [16] $end
$var wire 1 4! operand_0 [15] $end
$var wire 1 5! operand_0 [14] $end
$var wire 1 6! operand_0 [13] $end
$var wire 1 7! operand_0 [12] $end
$var wire 1 8! operand_0 [11] $end
$var wire 1 9! operand_0 [10] $end
$var wire 1 :! operand_0 [9] $end
$var wire 1 ;! operand_0 [8] $end
$var wire 1 <! operand_0 [7] $end
$var wire 1 =! operand_0 [6] $end
$var wire 1 >! operand_0 [5] $end
$var wire 1 ?! operand_0 [4] $end
$var wire 1 @! operand_0 [3] $end
$var wire 1 A! operand_0 [2] $end
$var wire 1 B! operand_0 [1] $end
$var wire 1 C! operand_0 [0] $end
$var wire 1 D! operand_1 [31] $end
$var wire 1 E! operand_1 [30] $end
$var wire 1 F! operand_1 [29] $end
$var wire 1 G! operand_1 [28] $end
$var wire 1 H! operand_1 [27] $end
$var wire 1 I! operand_1 [26] $end
$var wire 1 J! operand_1 [25] $end
$var wire 1 K! operand_1 [24] $end
$var wire 1 L! operand_1 [23] $end
$var wire 1 M! operand_1 [22] $end
$var wire 1 N! operand_1 [21] $end
$var wire 1 O! operand_1 [20] $end
$var wire 1 P! operand_1 [19] $end
$var wire 1 Q! operand_1 [18] $end
$var wire 1 R! operand_1 [17] $end
$var wire 1 S! operand_1 [16] $end
$var wire 1 T! operand_1 [15] $end
$var wire 1 U! operand_1 [14] $end
$var wire 1 V! operand_1 [13] $end
$var wire 1 W! operand_1 [12] $end
$var wire 1 X! operand_1 [11] $end
$var wire 1 Y! operand_1 [10] $end
$var wire 1 Z! operand_1 [9] $end
$var wire 1 [! operand_1 [8] $end
$var wire 1 \! operand_1 [7] $end
$var wire 1 ]! operand_1 [6] $end
$var wire 1 ^! operand_1 [5] $end
$var wire 1 _! operand_1 [4] $end
$var wire 1 `! operand_1 [3] $end
$var wire 1 a! operand_1 [2] $end
$var wire 1 b! operand_1 [1] $end
$var wire 1 c! operand_1 [0] $end
$var reg 32 d! result [31:0] $end
$upscope $end
$upscope $end
$enddefinitions $end
#0
$dumpvars
b0 A
b1100001000010011000010010010001 B
b1110101100000010100101000101011 C
b11010110100010101100111010111100 d!
b0 o
b1100001000010011000010010010001 p
b1110101100000010100101000101011 q
bx r
bx s
b0 !
b1 "
b10 #
b11 $
b100 %
b101 &
b110 '
b111 (
b1000 )
b0 u
b1 v
b10 w
b11 x
b100 y
b101 z
b110 {
b111 |
b1000 }
b1011100010111000101111011101000110010101110011011101000010111101101001011011100111000001110101011101000101111101100100011000010111010001100001001011110100000101000100010001000101111101001111010100000100010101010010010000010100111001000100010111110011000000101110011101000111100001110100 *
b1011100010111000101111011101000110010101110011011101000010111101101001011011100111000001110101011101000101111101100100011000010111010001100001001011110100000101000100010001000101111101001111010100000100010101010010010000010100111001000100010111110011000100101110011101000111100001110100 +
b1011100010111000101111011101000110010101110011011101000010111101101001011011100111000001110101011101000101111101100100011000010111010001100001001011110100000101000100010001000101111101010010010001010101001101010101010011000101010000101110011101000111100001110100 ,
b1011100010111000101111011101000110010101110011011101000010111101101001011011100111000001110101011101000101111101100100011000010111010001100001001011110101001101010101010000100101111101001111010100000100010101010010010000010100111001000100010111110011000000101110011101000111100001110100 -
b1011100010111000101111011101000110010101110011011101000010111101101001011011100111000001110101011101000101111101100100011000010111010001100001001011110101001101010101010000100101111101001111010100000100010101010010010000010100111001000100010111110011000100101110011101000111100001110100 .
b1011100010111000101111011101000110010101110011011101000010111101101001011011100111000001110101011101000101111101100100011000010111010001100001001011110101001101010101010000100101111101010010010001010101001101010101010011000101010000101110011101000111100001110100 /
b101110001011100010111101110100011001010111001101110100001011110110100101101110011100000111010101110100010111110110010001100001011101000110000100101111010000100100100101010100010101110100100101010011010001010101111101001111010100000100010101010010010000010100111001000100010111110011000000101110011101000111100001110100 0
b101110001011100010111101110100011001010111001101110100001011110110100101101110011100000111010101110100010111110110010001100001011101000110000100101111010000100100100101010100010101110100100101010011010001010101111101001111010100000100010101010010010000010100111001000100010111110011000100101110011101000111100001110100 1
b1011100010111000101111011101000110010101110011011101000010111101101001011011100111000001110101011101000101111101100100011000010111010001100001001011110100000101001110010001000101111101010010010001010101001101010101010011000101010000101110011101000111100001110100 2
b10111000101110001011110111010001100101011100110111010000101111011010010110111001110000011101010111010001011111011001000110000101110100011000010010111101001111010100100101111101010010010001010101001101010101010011000101010000101110011101000111100001110100 3
b1011100010111000101111011101000110010101110011011101000010111101101001011011100111000001110101011101000101111101100100011000010111010001100001001011110101100001001111010100100101111101010010010001010101001101010101010011000101010000101110011101000111100001110100 4
b10111000101110001011110111010001100101011100110111010000101111011010010110111001110000011101010111010001011111011001000110000101110100011000010010111101010011010010000100110001011111010011000100111101000111010010010100001101000001010011000101111101001111010100000100010101010010010000010100111001000100010111110011000000101110011101000111100001110100 5
b10111000101110001011110111010001100101011100110111010000101111011010010110111001110000011101010111010001011111011001000110000101110100011000010010111101010011010010000100110001011111010011000100111101000111010010010100001101000001010011000101111101001111010100000100010101010010010000010100111001000100010111110011000100101110011101000111100001110100 6
b10111000101110001011110111010001100101011100110111010000101111011010010110111001110000011101010111010001011111011001000110000101110100011000010010111101010011010010000100110001011111010011000100111101000111010010010100001101000001010011000101111101010010010001010101001101010101010011000101010000101110011101000111100001110100 7
b10111000101110001011110111010001100101011100110111010000101111011010010110111001110000011101010111010001011111011001000110000101110100011000010010111101010011010010000101001001011111010011000100111101000111010010010100001101000001010011000101111101001111010100000100010101010010010000010100111001000100010111110011000000101110011101000111100001110100 8
b10111000101110001011110111010001100101011100110111010000101111011010010110111001110000011101010111010001011111011001000110000101110100011000010010111101010011010010000101001001011111010011000100111101000111010010010100001101000001010011000101111101001111010100000100010101010010010000010100111001000100010111110011000100101110011101000111100001110100 9
b10111000101110001011110111010001100101011100110111010000101111011010010110111001110000011101010111010001011111011001000110000101110100011000010010111101010011010010000101001001011111010011000100111101000111010010010100001101000001010011000101111101010010010001010101001101010101010011000101010000101110011101000111100001110100 :
b10111000101110001011110111010001100101011100110111010000101111011010010110111001110000011101010111010001011111011001000110000101110100011000010010111101010011010010000101001001011111010000010101001001001001010101000100100001001101010001010101010001001001010000110101111101001111010100000100010101010010010000010100111001000100010111110011000000101110011101000111100001110100 ;
b10111000101110001011110111010001100101011100110111010000101111011010010110111001110000011101010111010001011111011001000110000101110100011000010010111101010011010010000101001001011111010000010101001001001001010101000100100001001101010001010101010001001001010000110101111101001111010100000100010101010010010000010100111001000100010111110011000100101110011101000111100001110100 <
b10111000101110001011110111010001100101011100110111010000101111011010010110111001110000011101010111010001011111011001000110000101110100011000010010111101010011010010000101001001011111010000010101001001001001010101000100100001001101010001010101010001001001010000110101111101010010010001010101001101010101010011000101010000101110011101000111100001110100 =
b1011100010111000101111011101000110010101110011011101000010111101101001011011100111000001110101011101000101111101100100011000010111010001100001001011110100110001000101010100110101001101011111010101000100100001000001010011100101111101001111010100000100010101010010010000010100111001000100010111110011000000101110011101000111100001110100 >
b1011100010111000101111011101000110010101110011011101000010111101101001011011100111000001110101011101000101111101100100011000010111010001100001001011110100110001000101010100110101001101011111010101000100100001000001010011100101111101001111010100000100010101010010010000010100111001000100010111110011000100101110011101000111100001110100 ?
b1011100010111000101111011101000110010101110011011101000010111101101001011011100111000001110101011101000101111101100100011000010111010001100001001011110100110001000101010100110101001101011111010101000100100001000001010011100101111101010010010001010101001101010101010011000101010000101110011101000111100001110100 @
b0 d
b0 e
b0 f
b0 g
b0 h
b0 i
b0 j
b0 k
b0 l
bx m
bx t
b0 n
0c
0b
1a
1`
1_
1^
0]
1\
0[
1Z
1Y
1X
0W
0V
1U
1T
0S
1R
0Q
1P
0O
0N
0M
1L
0K
1J
1I
0H
1G
0F
1E
1D
1c!
1b!
0a!
1`!
0_!
1^!
0]!
0\!
0[!
1Z!
0Y!
1X!
0W!
0V!
1U!
0T!
1S!
0R!
0Q!
0P!
0O!
0N!
0M!
1L!
1K!
0J!
1I!
0H!
1G!
1F!
1E!
0D!
1C!
0B!
0A!
0@!
1?!
0>!
0=!
1<!
0;!
0:!
19!
08!
07!
06!
05!
14!
13!
02!
01!
10!
0/!
0.!
0-!
0,!
1+!
0*!
0)!
0(!
0'!
1&!
1%!
0$!
0#!
0"!
0!!
0~
$end
#1
b11010110100010101100111010111100 r
b11010110100010101100111010111100 s
b0 t
b1 t
b1 d
b1 n
b10110100010110010001110100110110 p
b10011010011010011010000011111101 q
b10110100010110010001110100110110 B
b10011010011010011010000011111101 C
0b!
1a!
1_!
1]!
1\!
0Z!
0X!
1V!
0U!
1T!
1P!
1N!
1M!
0L!
0K!
1J!
0I!
1H!
0F!
0E!
1D!
0C!
1B!
1A!
1>!
0<!
1;!
18!
17!
04!
1/!
1-!
0+!
1)!
1'!
0%!
1$!
b1001110110000101011111000110011 d!
1c
1b
0a
0`
0\
1W
1V
0U
0P
1M
1H
0G
0D
#2
b1001110110000101011111000110011 r
b1001110110000101011111000110011 s
b10 t
b10 d
b10 n
b11100010101000011110101110001011 p
b11101001110000110100001001010001 q
b11100010101000011110101110001011 B
b11101001110000110100001001010001 C
0a!
0`!
0^!
0\!
1Z!
0V!
1U!
0T!
1R!
0P!
0N!
1L!
1K!
0J!
0G!
1F!
1E!
1C!
0A!
1@!
0?!
0>!
1<!
1:!
09!
07!
16!
15!
14!
00!
0/!
1.!
0-!
1,!
1*!
0)!
0'!
1%!
b11001100011001010010110111011100 d!
0c
0b
1a
1`
0^
1]
1\
1[
0Z
0W
0T
1S
0R
1Q
1N
0L
0J
1D
#3
b11001100011001010010110111011100 r
b11001100011001010010110111011100 s
b11 t
b11 d
b11 n
b11100111000111111110010011010010 p
b10011010111100111100011111011101 q
b11100111000111111110010011010010 B
b10011010111100111100011111011101 C
1a!
1`!
1\!
1[!
1Y!
1T!
1O!
1N!
0K!
1J!
1G!
0F!
0E!
0C!
0@!
1?!
1=!
0;!
0:!
19!
08!
12!
11!
10!
1/!
0.!
0,!
1+!
1)!
b10000010000100111010110010101111 d!
1c
1b
0_
1^
0]
0[
1T
1R
0Q
1O
0N
0M
1J
0I
0H
0E
#4
b10000010000100111010110010101111 r
b10000010000100111010110010101111 s
b100 t
b100 d
b100 n
b1110000100110100111111111110101 p
b1111000100011101110110010100100 q
b1110000100110100111111111110101 B
b1111000100011101110110010100100 C
0c!
0`!
0_!
1^!
0]!
0[!
0Z!
1X!
1V!
0S!
1Q!
1P!
0O!
0N!
0M!
0J!
1F!
1E!
0D!
1C!
0B!
1A!
1>!
1;!
1:!
18!
17!
04!
03!
01!
1,!
0+!
0*!
0)!
1'!
0$!
b11101001001010010110110010011001 d!
0b
0a
1_
0^
1U
0T
0R
1P
0O
1N
1K
0J
1H
1F
1E
#5
b11101001001010010110110010011001 r
b11101001001010010110110010011001 s
b101 t
b101 d
b101 n
b10111011101011000111011110001 p
b11111000101111100110010011011101 q
b10111011101011000111011110001 B
b11111000101111100110010011011101 C
1c!
1`!
1_!
0^!
1]!
0X!
0T!
1O!
1N!
1D!
0A!
0;!
07!
06!
05!
14!
13!
02!
11!
00!
1.!
1-!
0,!
1+!
1*!
1)!
0&!
0%!
b10000001100111111001111001110 d!
0c
1b
1a
0_
1]
1[
1Z
0Y
0X
1W
1T
1R
0P
1O
0K
0H
1G
0F
0E
0D
#6
b10000001100111111001111001110 r
b10000001100111111001111001110 s
b110 t
b110 d
b110 n
b10011100111110011110100011001110 p
b11111111010111100000111110011 q
b10011100111110011110100011001110 B
b11111111010111100000111110011 C
1b!
0a!
0`!
1^!
1[!
0Y!
0V!
1T!
1S!
0Q!
0O!
1M!
1K!
1J!
1I!
0F!
0E!
0D!
0C!
1B!
1A!
1@!
0?!
0>!
0:!
09!
16!
15!
01!
10!
1,!
0+!
0*!
1(!
1$!
b10111100111001011010101011000001 d!
1c
0b
0a
0`
0[
1X
0W
0U
0R
1Q
0O
1M
1L
1I
1H
1F
1D
#7
b10111100111001011010101011000001 r
b10111100111001011010101011000001 s
b111 t
b111 d
b111 n
b100010100101001100001101011011 p
b11101100100110001010100111001 q
b100010100101001100001101011011 B
b11101100100110001010100111001 C
0b!
1`!
0]!
0\!
1Y!
1W!
0U!
0T!
0P!
1O!
0N!
0M!
0J!
1C!
0A!
1?!
0<!
1;!
1:!
08!
06!
03!
11!
00!
0.!
0-!
1*!
0)!
0(!
0'!
1&!
0$!
b1000000001001111101100010010100 d!
0c
1a
1_
0]
0Z
1W
0V
1U
1R
0M
0L
0I
0H
0G
0F
1E
0D
#8
b1000000001001111101100010010100 r
b1000000001001111101100010010100 s
b1000 t
b1000 d
b1000 n
b10111000111100101010011100010101 p
b1111010000100100101111110101010 q
b10111000111100101010011100010101 B
b1111010000100100101111110101010 C
0c!
1b!
0_!
1\!
1Z!
1X!
1U!
0S!
0L!
0K!
1J!
0I!
1F!
1E!
0B!
1A!
0@!
0=!
19!
16!
05!
12!
01!
1.!
1-!
0*!
1(!
1'!
1$!
b110011000001010000011010111111 d!
1c
1b
1`
1^
1Z
1Y
0X
0W
0U
0T
0R
0N
1K
1J
1G
1F
0E
